<?xml version="1.0" encoding="UTF-8"?>
<window type="dialog" id="1183">
	<onload condition="[Control.HasFocus(595) | Control.HasFocus(587) | Control.HasFocus(596) | Control.HasFocus(504) | Control.HasFocus(590) | Control.HasFocus(597) | Control.HasFocus(501) | Control.HasFocus(594) | Control.HasFocus(593)] + Player.Playing">Stop</onload>
	<onload condition="Control.HasFocus(595) | Control.HasFocus(587) | Control.HasFocus(596) | Control.HasFocus(504) | Control.HasFocus(590) | Control.HasFocus(597) | Control.HasFocus(501) | Control.HasFocus(594) | Control.HasFocus(593)">SetProperty(What_trailer,$INFO[ListItem.Trailer],home)</onload>
	<onload condition="Control.HasFocus(595) | Control.HasFocus(587) | Control.HasFocus(596) | Control.HasFocus(504) | Control.HasFocus(590) | Control.HasFocus(597) | Control.HasFocus(501) | Control.HasFocus(594) | Control.HasFocus(593)">PlayMedia($INFO[ListItem.Trailer],1)</onload>
	<onload condition="Control.HasFocus(595) | Control.HasFocus(587) | Control.HasFocus(596) | Control.HasFocus(504) | Control.HasFocus(590) | Control.HasFocus(597) | Control.HasFocus(501) | Control.HasFocus(594) | Control.HasFocus(593)">ClearProperty(theme_yes,home)</onload>
	<visible>!System.IdleTime(30) + System.IdleTime(4) + !String.IsEmpty(ListItem.Trailer) + Skin.HasSetting(playTrailer) + String.IsEmpty(Window(Home).Property(MediaMenu))</visible>
	<visible>!Window.IsActive(movieinformation)</visible>
	<visible>!System.HasActiveModalDialog</visible>
	<visible>!ListItem.IsCollection</visible>
	<visible>!ListItem.IsParentFolder</visible>
	<visible>String.IsEqual(Container.Viewmode,Shelf) | String.IsEqual(Container.Viewmode,CenterList) | String.IsEqual(Container.Viewmode,RightList) | String.IsEqual(Container.Viewmode,FanWall) | [String.IsEqual(Container.Viewmode,Triple) + String.IsEqual(ListItem.DBTYPE,movie)] | String.IsEqual(Container.Viewmode,Fanart) | String.IsEqual(Container.Viewmode,Wall) | String.IsEqual(Container.Viewmode,Banner) | String.IsEqual(Container.Viewmode,Flix)</visible>
	<visible>!String.IsEqual(Player.Filename,theme.mp3)</visible>
	<visible>!String.IsEqual(Skin.String(StartTrailer),10)</visible>
	<controls/>
</window>
